{"success":true,"updatedAt":"2026-07-05T17:44:01.209Z","data":{"today":{"pageViews":2,"users":1,"newUsers":1,"avgDuration":"0:03","bounceRate":"100.0%","sessions":1},"yesterday":{"pageViews":44,"users":19,"newUsers":16,"avgDuration":"0:55","bounceRate":"100.0%","sessions":19},"last7days":{"pageViews":286,"users":97,"newUsers":89,"avgDuration":"2:23","bounceRate":"26.3%","sessions":118},"last30days":{"pageViews":1700,"users":382,"newUsers":363,"avgDuration":"2:36","bounceRate":"26.1%","sessions":556},"allTime":{"pageViews":3753,"users":550,"newUsers":532,"avgDuration":"3:07","bounceRate":"29.8%","sessions":916},"realtime":{"activeUsers":1,"pageViews":1,"topPage":"REVELATION"},"trafficSources":[{"name":"Direct","value":379,"trend":0},{"name":"Unassigned","value":20,"trend":0}],"devices":[{"name":"mobile","value":327,"trend":0},{"name":"desktop","value":53,"trend":0},{"name":"tablet","value":2,"trend":0}],"countries":[{"name":"United States","code":"US","value":227},{"name":"China","code":"CN","value":140},{"name":"Canada","code":"CA","value":10},{"name":"Hong Kong","code":"","value":6},{"name":"India","code":"IN","value":2},{"name":"United Kingdom","code":"GB","value":2}],"cities":[{"name":"(not set)","value":182,"trend":0},{"name":"Council Bluffs","value":18,"trend":0},{"name":"Shenzhen","value":14,"trend":0},{"name":"Dongguan","value":13,"trend":0},{"name":"","value":10,"trend":0},{"name":"Chengdu","value":10,"trend":0},{"name":"New York","value":10,"trend":0},{"name":"Calgary","value":8,"trend":0},{"name":"Guangzhou","value":8,"trend":0},{"name":"Wantagh","value":8,"trend":0}],"topPages":[{"path":"/","views":586,"users":323,"avgDuration":"0:59","bounceRate":"13.9%"},{"path":"/index-1.html","views":518,"users":259,"avgDuration":"0:26","bounceRate":"12.2%"},{"path":"/game","views":226,"users":49,"avgDuration":"2:35","bounceRate":"20.0%"},{"path":"/mj/g2","views":95,"users":38,"avgDuration":"1:05","bounceRate":"17.5%"},{"path":"/mj/g1","views":64,"users":32,"avgDuration":"0:41","bounceRate":"15.2%"},{"path":"/index-2.html","views":47,"users":34,"avgDuration":"0:19","bounceRate":"5.1%"},{"path":"/index-3.html","views":43,"users":32,"avgDuration":"0:12","bounceRate":"11.8%"},{"path":"/mj/g2-2","views":40,"users":25,"avgDuration":"0:33","bounceRate":"35.5%"},{"path":"/__virtual_fs__/6a3a55f33ed665542a295a1b/GAME.html","views":32,"users":1,"avgDuration":"7:49","bounceRate":"64.7%"},{"path":"/__virtual_fs__/6a421924d030b2683827ee1e/GAME.html","views":25,"users":1,"avgDuration":"14:54","bounceRate":"60.0%"}],"browsers":[{"name":"Chrome","value":274,"trend":0},{"name":"Android Webview","value":71,"trend":0},{"name":"Edge","value":20,"trend":0},{"name":"Safari","value":12,"trend":0},{"name":"Safari (in-app)","value":9,"trend":0}],"operatingSystems":[{"name":"iOS","value":227,"trend":0},{"name":"Android","value":106,"trend":0},{"name":"Windows","value":32,"trend":0},{"name":"Linux","value":20,"trend":0},{"name":"Macintosh","value":1,"trend":0}],"events":[{"name":"page_view","category":"page","count":1700,"users":382},{"name":"scroll","category":"engagement","count":1109,"users":220},{"name":"user_engagement","category":"other","count":932,"users":126},{"name":"session_start","category":"session","count":543,"users":379},{"name":"first_visit","category":"user","count":363,"users":363}]}}